CHANGELOG.rst
LICENSE
MANIFEST.in
README.rst
setup.cfg
setup.py
cliquet_pusher/__init__.py
cliquet_pusher/listener.py
cliquet_pusher.egg-info/PKG-INFO
cliquet_pusher.egg-info/SOURCES.txt
cliquet_pusher.egg-info/dependency_links.txt
cliquet_pusher.egg-info/not-zip-safe
cliquet_pusher.egg-info/pbr.json
cliquet_pusher.egg-info/requires.txt
cliquet_pusher.egg-info/top_level.txt
tests/__init__.py