Metadata-Version: 1.1
Name: cliquet-pusher
Version: 0.2.0
Summary: Plug Cliquet notifications with Pusher.com
Home-page: https://github.com/leplatrem/cliquet-pusher
Author: Mathieu Leplatre
Author-email: mathieu@leplat.re
License: Apache License (2.0)
Keywords: cliquet pusher
Platform: UNKNOWN
Classifier: Development Status :: 2 - Pre-Alpha
Classifier: Intended Audience :: Developers
Classifier: License :: OSI Approved :: Apache Software License
Classifier: Natural Language :: English
Classifier: Programming Language :: Python :: 2
Classifier: Programming Language :: Python :: 2.6
Classifier: Programming Language :: Python :: 2.7
Classifier: Programming Language :: Python :: 3
Classifier: Programming Language :: Python :: 3.3
Classifier: Programming Language :: Python :: 3.4
Classifier: Programming Language :: Python :: 3.5
